{
  "status":"success",
  "data":{
    "query":{
      "locale":"en_us",
      "query":"dogs",
      "offset":40
    },
    "cache":{
      "key":"40f564d121e0c214f67a951b8cb5bfbf",
      "created":1551108634,
      "expiration":2592000,
      "status":"miss",
      "age":0
    },
    "result":{
      "total":40,
      "items":[
        {
          "title":"no dogs on the sofa &laquo; Love and a Six-Foot Leash",
          "type":"image",
          "media":"https:\/\/loveandaleash.files.wordpress.com\/2011\/09\/little-zee-110919-14.jpg",
          "desc":"",
          "thumbnail":"\/\/s2.qwant.com\/thumbr\/301x200\/4\/1\/a65f632e04a9134ce5bfd53e6d02949fbb381516163fa88d38a507d1864fd5\/little-zee-110919-14.jpg?u=https%3A%2F%2Floveandaleash.files.wordpress.com%2F2011%2F09%2Flittle-zee-110919-14.jpg&q=0&b=1&p=0&a=0&b_id=OIP.mpEgDuf0BGfFzS3jDrRnOAHaE6",
          "thumb_width":301,
          "thumb_height":200,
          "width":"4288",
          "height":"2848",
          "size":"7782718",
          "url":"https:\/\/loveandaleash.com\/2011\/09\/26\/no-dogs-on-the-sofa\/",
          "_id":"dc129bfdf49c7acf1ceccf6309e7dfbe",
          "b_id":"OIP.mpEgDuf0BGfFzS3jDrRnOAHaE6",
          "media_fullsize":"\/\/s2.qwant.com\/thumbr\/0x0\/d\/3\/e2670636cfc8333ace7b15ecceaafec38adf912dbd3f2c3f03532854e40904\/little-zee-110919-14.jpg?u=https%3A%2F%2Floveandaleash.files.wordpress.com%2F2011%2F09%2Flittle-zee-110919-14.jpg&q=0&b=1&p=0&a=1",
          "thumb_type":"jpg",
          "count":40,
          "media_preview":"\/\/s2.qwant.com\/thumbr\/0x380\/e\/3\/48bad4f45751a7699fec4f4f556c2a7a8b1995b775832d860f9236b9383425\/little-zee-110919-14.jpg?u=https%3A%2F%2Floveandaleash.files.wordpress.com%2F2011%2F09%2Flittle-zee-110919-14.jpg&q=0&b=1&p=0&a=1"
        },
        {
          "title":"Is the Eurasier dog a good choice of pet? | Pets4Homes",
          "type":"image",
          "media":"https:\/\/www.pets4homes.co.uk\/images\/articles\/2448\/large\/is-the-eurasier-dog-a-good-choice-of-pet-54a92055275c0.jpg",
          "desc":"",
          "thumbnail":"\/\/s2.qwant.com\/thumbr\/301x200\/c\/3\/0a77928570a5e95d93d6bdb421a068f3ca9ce60fc35070feaf035551c1fcb9\/is-the-eurasier-dog-a-good-choice-of-pet-54a92055275c0.jpg?u=https%3A%2F%2Fwww.pets4homes.co.uk%2Fimages%2Farticles%2F2448%2Flarge%2Fis-the-eurasier-dog-a-good-choice-of-pet-54a92055275c0.jpg&q=0&b=1&p=0&a=0&b_id=OIP.tRRoDxFAAIUUZSzt_hAYsQHaE6",
          "thumb_width":301,
          "thumb_height":200,
          "width":"1280",
          "height":"850",
          "size":"130430",
          "url":"https:\/\/www.pets4homes.co.uk\/pet-advice\/is-the-eurasier-dog-a-good-choice-of-pet.html",
          "_id":"12f862e53696e1654392ea4782cca41e",
          "b_id":"OIP.tRRoDxFAAIUUZSzt_hAYsQHaE6",
          "media_fullsize":"\/\/s2.qwant.com\/thumbr\/0x0\/6\/1\/86f5a6b42b8febb7c4bdd0b4738ce4846124c7c2f48a66c21eb93be39ac3f4\/is-the-eurasier-dog-a-good-choice-of-pet-54a92055275c0.jpg?u=https%3A%2F%2Fwww.pets4homes.co.uk%2Fimages%2Farticles%2F2448%2Flarge%2Fis-the-eurasier-dog-a-good-choice-of-pet-54a92055275c0.jpg&q=0&b=1&p=0&a=1",
          "thumb_type":"jpg",
          "count":42,
          "media_preview":"\/\/s1.qwant.com\/thumbr\/0x380\/b\/c\/b8c2abc33e6243f487af1172bd1afbfe87d6b60876b4539c3091915af7081d\/is-the-eurasier-dog-a-good-choice-of-pet-54a92055275c0.jpg?u=https%3A%2F%2Fwww.pets4homes.co.uk%2Fimages%2Farticles%2F2448%2Flarge%2Fis-the-eurasier-dog-a-good-choice-of-pet-54a92055275c0.jpg&q=0&b=1&p=0&a=1"
        },
        {
          "title":"Dogs In Basket Wallpapers High Quality | Download Free",
          "type":"image",
          "media":"http:\/\/yesofcorsa.com\/wp-content\/uploads\/2017\/06\/Dogs-In-Basket-Wallpaper-HQ.jpg",
          "desc":"",
          "thumbnail":"\/\/s2.qwant.com\/thumbr\/355x200\/c\/3\/2294d8ed2e2bff77fa45b17c2679b115323a8afa87aba06870bd2cf7678e02\/Dogs-In-Basket-Wallpaper-HQ.jpg?u=http%3A%2F%2Fyesofcorsa.com%2Fwp-content%2Fuploads%2F2017%2F06%2FDogs-In-Basket-Wallpaper-HQ.jpg&q=0&b=1&p=0&a=0&b_id=OIP.g-C6IKILcRAAeZfbWN5JrQHaEK",
          "thumb_width":355,
          "thumb_height":200,
          "width":"1600",
          "height":"900",
          "size":"365791",
          "url":"http:\/\/yesofcorsa.com\/dogs-in-basket\/",
          "_id":"49245e876fe03a7beff617cc07313d56",
          "b_id":"OIP.g-C6IKILcRAAeZfbWN5JrQHaEK",
          "media_fullsize":"\/\/s1.qwant.com\/thumbr\/0x0\/2\/d\/fdffb17d3ebef813c1ec7abd29f2fce5f7263ebaceed87a002b8ed51bc3295\/Dogs-In-Basket-Wallpaper-HQ.jpg?u=http%3A%2F%2Fyesofcorsa.com%2Fwp-content%2Fuploads%2F2017%2F06%2FDogs-In-Basket-Wallpaper-HQ.jpg&q=0&b=1&p=0&a=1",
          "thumb_type":"jpg",
          "count":43,
          "media_preview":"\/\/s1.qwant.com\/thumbr\/0x380\/2\/9\/206a856643c90065440ae2fc4633db695dee73b1c2d10c822335a7e1538723\/Dogs-In-Basket-Wallpaper-HQ.jpg?u=http%3A%2F%2Fyesofcorsa.com%2Fwp-content%2Fuploads%2F2017%2F06%2FDogs-In-Basket-Wallpaper-HQ.jpg&q=0&b=1&p=0&a=1"
        },
        {
          "title":"Samoyed - Dogs breeds | Pets",
          "type":"image",
          "media":"https:\/\/www.mascotarios.org\/wp-content\/gallery\/samoyedo\/samoyedo6.jpg",
          "desc":"",
          "thumbnail":"\/\/s2.qwant.com\/thumbr\/266x200\/4\/a\/64cd3366277e732efd9065adda4e967d7f6aa09c72bc87af7b649f721e20c7\/samoyedo6.jpg?u=https%3A%2F%2Fwww.mascotarios.org%2Fwp-content%2Fgallery%2Fsamoyedo%2Fsamoyedo6.jpg&q=0&b=1&p=0&a=0&b_id=OIP.wpnKIqUTVOhoD92S_7aWjgHaFj",
          "thumb_width":266,
          "thumb_height":200,
          "width":"1024",
          "height":"768",
          "size":"195843",
          "url":"http:\/\/www.mascotarios.org\/en\/samoyedo\/",
          "_id":"6fc8e48cdb3142236b707ad8d6879cfd",
          "b_id":"OIP.wpnKIqUTVOhoD92S_7aWjgHaFj",
          "media_fullsize":"\/\/s2.qwant.com\/thumbr\/0x0\/c\/5\/cf485986563680be37d953ac7b7f2ade0b1db2c3d311c2605b6f0db9bfdb3b\/samoyedo6.jpg?u=https%3A%2F%2Fwww.mascotarios.org%2Fwp-content%2Fgallery%2Fsamoyedo%2Fsamoyedo6.jpg&q=0&b=1&p=0&a=1",
          "thumb_type":"jpg",
          "count":44,
          "media_preview":"\/\/s2.qwant.com\/thumbr\/0x380\/e\/e\/3159bbe9e653dbc158f32ef9b26f115d71eefe707f612b1ac1f9f2006d8acc\/samoyedo6.jpg?u=https%3A%2F%2Fwww.mascotarios.org%2Fwp-content%2Fgallery%2Fsamoyedo%2Fsamoyedo6.jpg&q=0&b=1&p=0&a=1"
        },
        {
          "title":"Download Cats &amp; Dogs (2001) YIFY Torrent for 1080p mp4 ...",
          "type":"image",
          "media":"https:\/\/pic.yify-torrent.org\/yt\/20160317\/26625\/screenshot2.png",
          "desc":"",
          "thumbnail":"\/\/s2.qwant.com\/thumbr\/355x200\/6\/d\/8557ec83598dcc9c6ffdcb1485842d1032bf492e5ad1fcff414722ded9be91\/screenshot2.png?u=https%3A%2F%2Fpic.yify-torrent.org%2Fyt%2F20160317%2F26625%2Fscreenshot2.png&q=0&b=1&p=0&a=0&b_id=OIP.aFLz4TcZfgFXaeYDtQ6-YAHaEK",
          "thumb_width":355,
          "thumb_height":200,
          "width":"1920",
          "height":"1080",
          "size":"2217121",
          "url":"https:\/\/www.yify-torrent.org\/movie\/41263\/download-cats-dogs-2001-1080p-mp4-yify-torrent.html",
          "_id":"dba69624039db7357670bb9ca1b4ea96",
          "b_id":"OIP.aFLz4TcZfgFXaeYDtQ6-YAHaEK",
          "media_fullsize":"\/\/s1.qwant.com\/thumbr\/0x0\/3\/f\/7eecbb1a979aa411ab20c81be963efb64350aeb3268644956d8bd9da33c5be\/screenshot2.png?u=https%3A%2F%2Fpic.yify-torrent.org%2Fyt%2F20160317%2F26625%2Fscreenshot2.png&q=0&b=1&p=0&a=1",
          "thumb_type":"png",
          "count":45,
          "media_preview":"\/\/s2.qwant.com\/thumbr\/0x380\/f\/3\/9173a5e6c5e42a889c013b6798e3d7d0443dee57b5fdb4c1d9b246f8731962\/screenshot2.png?u=https%3A%2F%2Fpic.yify-torrent.org%2Fyt%2F20160317%2F26625%2Fscreenshot2.png&q=0&b=1&p=0&a=1"
        },
        {
          "title":"Springador Dog Breed Information, Buying Advice, Photos ...",
          "type":"image",
          "media":"http:\/\/www.pets4homes.co.uk\/images\/breeds\/338\/large\/37a7b2a798a415feea212f7c3a9e6baf.jpg",
          "desc":"",
          "thumbnail":"\/\/s2.qwant.com\/thumbr\/318x200\/e\/f\/accbcc2c7404d75ba77051eb2a1fc59ac14b505e43d5932e7e2af18b49bb39\/37a7b2a798a415feea212f7c3a9e6baf.jpg?u=http%3A%2F%2Fwww.pets4homes.co.uk%2Fimages%2Fbreeds%2F338%2Flarge%2F37a7b2a798a415feea212f7c3a9e6baf.jpg&q=0&b=1&p=0&a=0&b_id=OIP.9w8nMQIzEJfmIA60ETaOzwHaEp",
          "thumb_width":318,
          "thumb_height":200,
          "width":"1280",
          "height":"804",
          "size":"126124",
          "url":"http:\/\/www.pets4homes.co.uk\/pets4homes\/home.nsf\/breedinfo\/springador",
          "_id":"3fc40d401ec22bd2590a899c36978a81",
          "b_id":"OIP.9w8nMQIzEJfmIA60ETaOzwHaEp",
          "media_fullsize":"\/\/s1.qwant.com\/thumbr\/0x0\/3\/0\/4d9fc0582509b8d9ba4964f396f2cd65636375545cebd16218269b5f68abc6\/37a7b2a798a415feea212f7c3a9e6baf.jpg?u=http%3A%2F%2Fwww.pets4homes.co.uk%2Fimages%2Fbreeds%2F338%2Flarge%2F37a7b2a798a415feea212f7c3a9e6baf.jpg&q=0&b=1&p=0&a=1",
          "thumb_type":"jpg",
          "count":46,
          "media_preview":"\/\/s2.qwant.com\/thumbr\/0x380\/4\/b\/9817ecd0a2aeb9470727be322775aee8889a9737b201eaf302c9ab026d2726\/37a7b2a798a415feea212f7c3a9e6baf.jpg?u=http%3A%2F%2Fwww.pets4homes.co.uk%2Fimages%2Fbreeds%2F338%2Flarge%2F37a7b2a798a415feea212f7c3a9e6baf.jpg&q=0&b=1&p=0&a=1"
        },
        {
          "title":"Science Says Dogs Can't Count but Cats Might, While Frogs ...",
          "type":"image",
          "media":"https:\/\/peopledotcom.files.wordpress.com\/2018\/02\/dogs.jpg",
          "desc":"",
          "thumbnail":"\/\/s1.qwant.com\/thumbr\/300x200\/8\/3\/f6381c2ea4eede1e09187bb6ba87fb097ca5fbc30a84ebf88cd18eeaabfe3f\/dogs.jpg?u=https%3A%2F%2Fpeopledotcom.files.wordpress.com%2F2018%2F02%2Fdogs.jpg&q=0&b=1&p=0&a=0&b_id=OIP.hHZJjFM_TSG0itTtMEwEIQHaE7",
          "thumb_width":300,
          "thumb_height":200,
          "width":"2000",
          "height":"1331",
          "size":"715003",
          "url":"https:\/\/people.com\/pets\/animals-can-count-dogs-cant-count\/",
          "_id":"77bc8f55f0648b837349404bd1440cbe",
          "b_id":"OIP.hHZJjFM_TSG0itTtMEwEIQHaE7",
          "media_fullsize":"\/\/s1.qwant.com\/thumbr\/0x0\/b\/8\/4d07fdfdbd637b163927abe2e4622c75a124dd34683104a46a61b3a3595624\/dogs.jpg?u=https%3A%2F%2Fpeopledotcom.files.wordpress.com%2F2018%2F02%2Fdogs.jpg&q=0&b=1&p=0&a=1",
          "thumb_type":"jpg",
          "count":47,
          "media_preview":"\/\/s2.qwant.com\/thumbr\/0x380\/6\/f\/0ea51de2880fbf9fe4384476e62d70c8e528c4256e5795670689cd7428644a\/dogs.jpg?u=https%3A%2F%2Fpeopledotcom.files.wordpress.com%2F2018%2F02%2Fdogs.jpg&q=0&b=1&p=0&a=1"
        },
        {
          "title":"Combai Dog Info, History, Temperament, Training, Puppy ...",
          "type":"image",
          "media":"https:\/\/www.101dogbreeds.com\/wp-content\/uploads\/2017\/07\/Combai.jpg",
          "desc":"",
          "thumbnail":"\/\/s2.qwant.com\/thumbr\/250x200\/c\/d\/2f47330e219e7361f2214a35efddcf18b7073ccaecfdf17a68ef45c36ef5d4\/Combai.jpg?u=https%3A%2F%2Fwww.101dogbreeds.com%2Fwp-content%2Fuploads%2F2017%2F07%2FCombai.jpg&q=0&b=1&p=0&a=0&b_id=OIP.GyB1trqNFVn56R9PeTxfAAHaF6",
          "thumb_width":250,
          "thumb_height":200,
          "width":"960",
          "height":"767",
          "size":"81552",
          "url":"https:\/\/www.101dogbreeds.com\/combai.asp",
          "_id":"b93c58e8814eeda39f06fe91270f2529",
          "b_id":"OIP.GyB1trqNFVn56R9PeTxfAAHaF6",
          "media_fullsize":"\/\/s1.qwant.com\/thumbr\/0x0\/3\/e\/012082bc0aa773534de70c7f0ac2ae516e56611f20b0c095bfa42ddffeed49\/Combai.jpg?u=https%3A%2F%2Fwww.101dogbreeds.com%2Fwp-content%2Fuploads%2F2017%2F07%2FCombai.jpg&q=0&b=1&p=0&a=1",
          "thumb_type":"jpg",
          "count":48,
          "media_preview":"\/\/s1.qwant.com\/thumbr\/0x380\/0\/8\/0fca0f9578c61ae5b8a4cc881eff98a5d5bbef897ef35b53cd41041830ea79\/Combai.jpg?u=https%3A%2F%2Fwww.101dogbreeds.com%2Fwp-content%2Fuploads%2F2017%2F07%2FCombai.jpg&q=0&b=1&p=0&a=1"
        },
        {
          "title":"Neapolitan Mastiff Dog Breed Information, Buying Advice ...",
          "type":"image",
          "media":"https:\/\/www.pets4homes.co.uk\/images\/breeds\/150\/large\/672adbdaf7cf2194415cfc19f01dfbbb.jpg",
          "desc":"",
          "thumbnail":"\/\/s2.qwant.com\/thumbr\/300x200\/6\/4\/aa04d1760ab3efcd9d9f3e5b7b2e71f8f1f9f07cb43b1d845fed80754671b3\/672adbdaf7cf2194415cfc19f01dfbbb.jpg?u=https%3A%2F%2Fwww.pets4homes.co.uk%2Fimages%2Fbreeds%2F150%2Flarge%2F672adbdaf7cf2194415cfc19f01dfbbb.jpg&q=0&b=1&p=0&a=0&b_id=OIP.5x0avP-Ph1M7RtOt_GdXlQHaE7",
          "thumb_width":300,
          "thumb_height":200,
          "width":"1280",
          "height":"853",
          "size":"126141",
          "url":"https:\/\/www.pets4homes.co.uk\/dog-breeds\/neapolitan-mastiff\/",
          "_id":"6e810fe4e35f9c5bfd68b82921fd9a2e",
          "b_id":"OIP.5x0avP-Ph1M7RtOt_GdXlQHaE7",
          "media_fullsize":"\/\/s1.qwant.com\/thumbr\/0x0\/9\/7\/ad5b8ee6e35020edc16e0fafc369e2f62a9bdfa15ab32a52e7db3daf24b719\/672adbdaf7cf2194415cfc19f01dfbbb.jpg?u=https%3A%2F%2Fwww.pets4homes.co.uk%2Fimages%2Fbreeds%2F150%2Flarge%2F672adbdaf7cf2194415cfc19f01dfbbb.jpg&q=0&b=1&p=0&a=1",
          "thumb_type":"jpg",
          "count":49,
          "media_preview":"\/\/s2.qwant.com\/thumbr\/0x380\/4\/0\/24df84554bba4589deddb9955b7491049eb53c562b5e812ff1af95f378f2bd\/672adbdaf7cf2194415cfc19f01dfbbb.jpg?u=https%3A%2F%2Fwww.pets4homes.co.uk%2Fimages%2Fbreeds%2F150%2Flarge%2F672adbdaf7cf2194415cfc19f01dfbbb.jpg&q=0&b=1&p=0&a=1"
        },
        {
          "title":"Eurasier Dog Breed &raquo; Everything About Eurasier",
          "type":"image",
          "media":"https:\/\/img.dog-learn.com\/dog-breeds\/eurasier\/eurasier-puppy-i2.jpg",
          "desc":"",
          "thumbnail":"\/\/s1.qwant.com\/thumbr\/288x200\/2\/9\/9eeee5982ffb343ad34a237e6c26424d966dbfa02ddde5f588548f01e815b2\/eurasier-puppy-i2.jpg?u=https%3A%2F%2Fimg.dog-learn.com%2Fdog-breeds%2Feurasier%2Feurasier-puppy-i2.jpg&q=0&b=1&p=0&a=0&b_id=OIP.A2XTQllP8XQta2XeqZQCYQHaFI",
          "thumb_width":288,
          "thumb_height":200,
          "width":"1280",
          "height":"888",
          "size":"75749",
          "url":"http:\/\/www.dog-learn.com\/dog-breeds\/eurasier\/",
          "_id":"d626b1c792f61ce842bd497c46cbd69e",
          "b_id":"OIP.A2XTQllP8XQta2XeqZQCYQHaFI",
          "media_fullsize":"\/\/s2.qwant.com\/thumbr\/0x0\/d\/4\/d422367e3e65017d5765b882fb4b0983f86c8e189101cfda84843e3b15ecdf\/eurasier-puppy-i2.jpg?u=https%3A%2F%2Fimg.dog-learn.com%2Fdog-breeds%2Feurasier%2Feurasier-puppy-i2.jpg&q=0&b=1&p=0&a=1",
          "thumb_type":"jpg",
          "count":50,
          "media_preview":"\/\/s1.qwant.com\/thumbr\/0x380\/9\/3\/60a5db216f4a0798cb4309f8114adc78656a747fe0a3f4dd39c33b6beacd6e\/eurasier-puppy-i2.jpg?u=https%3A%2F%2Fimg.dog-learn.com%2Fdog-breeds%2Feurasier%2Feurasier-puppy-i2.jpg&q=0&b=1&p=0&a=1"
        },
        {
          "title":"Beauceron - Dogs breeds | Pets",
          "type":"image",
          "media":"https:\/\/www.mascotarios.org\/wp-content\/gallery\/beauceron\/beauceron2.jpg",
          "desc":"",
          "thumbnail":"\/\/s1.qwant.com\/thumbr\/266x200\/a\/4\/ac522bb8d7599069ccedb458d2992c6fceebdd91c0637bac9bba4489ee7753\/beauceron2.jpg?u=https%3A%2F%2Fwww.mascotarios.org%2Fwp-content%2Fgallery%2Fbeauceron%2Fbeauceron2.jpg&q=0&b=1&p=0&a=0&b_id=OIP.LRFOsy5wDYpUptnDwTT9-wHaFj",
          "thumb_width":266,
          "thumb_height":200,
          "width":"1024",
          "height":"768",
          "size":"40754",
          "url":"http:\/\/www.mascotarios.org\/en\/beauceron\/",
          "_id":"c55bbe9bbb7eff9bcff6f9d1406093ad",
          "b_id":"OIP.LRFOsy5wDYpUptnDwTT9-wHaFj",
          "media_fullsize":"\/\/s1.qwant.com\/thumbr\/0x0\/b\/0\/e0aeab0c0ad590cc070b6657506f5345a2bd2cc634922a110bfb57f71d7da5\/beauceron2.jpg?u=https%3A%2F%2Fwww.mascotarios.org%2Fwp-content%2Fgallery%2Fbeauceron%2Fbeauceron2.jpg&q=0&b=1&p=0&a=1",
          "thumb_type":"jpg",
          "count":51,
          "media_preview":"\/\/s1.qwant.com\/thumbr\/0x380\/2\/0\/af8ac6d181f12f9bc971511ebdd89cc9d3d8002a8fecd7e5353f2ddb0fed4c\/beauceron2.jpg?u=https%3A%2F%2Fwww.mascotarios.org%2Fwp-content%2Fgallery%2Fbeauceron%2Fbeauceron2.jpg&q=0&b=1&p=0&a=1"
        },
        {
          "title":"Bolognese | Dog Breed Facts, Highlights &amp; Advice | Pets4Homes",
          "type":"image",
          "media":"https:\/\/www.pets4homes.co.uk\/images\/breeds\/200\/large\/198cc3ca23540a1cf26594b77875a8fe.jpg",
          "desc":"",
          "thumbnail":"\/\/s1.qwant.com\/thumbr\/300x200\/9\/9\/eada41768e2453dbfb3a1135d2021e81b93d8f67645372ca171f11e19d6302\/198cc3ca23540a1cf26594b77875a8fe.jpg?u=https%3A%2F%2Fwww.pets4homes.co.uk%2Fimages%2Fbreeds%2F200%2Flarge%2F198cc3ca23540a1cf26594b77875a8fe.jpg&q=0&b=1&p=0&a=0&b_id=OIP.V0L6ysdvL9QEpU-ik4cpZAHaE7",
          "thumb_width":300,
          "thumb_height":200,
          "width":"1280",
          "height":"853",
          "size":"134603",
          "url":"https:\/\/www.pets4homes.co.uk\/dog-breeds\/bolognese\/",
          "_id":"14e0f9f33aaa7b27018962aab01f068e",
          "b_id":"OIP.V0L6ysdvL9QEpU-ik4cpZAHaE7",
          "media_fullsize":"\/\/s1.qwant.com\/thumbr\/0x0\/1\/7\/913c253121699ab6eaf25ed41c3b1769b26faefcca2b8956f86601f743f7ba\/198cc3ca23540a1cf26594b77875a8fe.jpg?u=https%3A%2F%2Fwww.pets4homes.co.uk%2Fimages%2Fbreeds%2F200%2Flarge%2F198cc3ca23540a1cf26594b77875a8fe.jpg&q=0&b=1&p=0&a=1",
          "thumb_type":"jpg",
          "count":52,
          "media_preview":"\/\/s1.qwant.com\/thumbr\/0x380\/9\/b\/78ee1dbac52a6ddea4432f78adca829e80a16ad280b0d66fed1b2fcd5671ad\/198cc3ca23540a1cf26594b77875a8fe.jpg?u=https%3A%2F%2Fwww.pets4homes.co.uk%2Fimages%2Fbreeds%2F200%2Flarge%2F198cc3ca23540a1cf26594b77875a8fe.jpg&q=0&b=1&p=0&a=1"
        },
        {
          "title":"Dogs Catching Treats - Squee!",
          "type":"image",
          "media":"http:\/\/www.squee.com\/wp-content\/uploads\/2016\/12\/dogs-catching-treats4.jpg",
          "desc":"",
          "thumbnail":"\/\/s1.qwant.com\/thumbr\/266x200\/2\/b\/5198f9a0c755ae6f227915060257d95dd4741fc91a56d6773cfd4135fd7166\/dogs-catching-treats4.jpg?u=http%3A%2F%2Fwww.squee.com%2Fwp-content%2Fuploads%2F2016%2F12%2Fdogs-catching-treats4.jpg&q=0&b=1&p=0&a=0&b_id=OIP.2aBfykvEZP7VGzZWFkDTfQHaFj",
          "thumb_width":266,
          "thumb_height":200,
          "width":"1200",
          "height":"901",
          "size":"108352",
          "url":"http:\/\/www.squee.com\/2016\/12\/07\/dogs-catching-treats\/",
          "_id":"32b850c189523c2fa8704c2f8147af50",
          "b_id":"OIP.2aBfykvEZP7VGzZWFkDTfQHaFj",
          "media_fullsize":"\/\/s1.qwant.com\/thumbr\/0x0\/8\/8\/b4bfb2cee8b17de3bbadd74ef2cb826b73aa0a218cca44eb53b25e1a9655ea\/dogs-catching-treats4.jpg?u=http%3A%2F%2Fwww.squee.com%2Fwp-content%2Fuploads%2F2016%2F12%2Fdogs-catching-treats4.jpg&q=0&b=1&p=0&a=1",
          "thumb_type":"jpg",
          "count":53,
          "media_preview":"\/\/s2.qwant.com\/thumbr\/0x380\/d\/0\/866e668b60af91bf777d34b78afe7223e87c2ae89f6c65a00504084268c70b\/dogs-catching-treats4.jpg?u=http%3A%2F%2Fwww.squee.com%2Fwp-content%2Fuploads%2F2016%2F12%2Fdogs-catching-treats4.jpg&q=0&b=1&p=0&a=1"
        },
        {
          "title":"23 Adorable Dogs In Hats [GALLERY] - Dogtime",
          "type":"image",
          "media":"http:\/\/cdn3-www.dogtime.com\/assets\/uploads\/2016\/03\/dog-in-hat-12.jpg",
          "desc":"",
          "thumbnail":"\/\/s2.qwant.com\/thumbr\/300x200\/d\/6\/033d3b88f2130d3d7fd1a56cc86c6278c338c09fd5e740aa894f83f2a2b21b\/dog-in-hat-12.jpg?u=http%3A%2F%2Fcdn3-www.dogtime.com%2Fassets%2Fuploads%2F2016%2F03%2Fdog-in-hat-12.jpg&q=0&b=1&p=0&a=0&b_id=OIP.GddkJOX8C37YLGHkUUGA-gHaE8",
          "thumb_width":300,
          "thumb_height":200,
          "width":"5760",
          "height":"3840",
          "size":"1343446",
          "url":"http:\/\/dogtime.com\/trending\/36289-23-adorable-dogs-hats-gallery",
          "_id":"7140db0e35e43a3effbbe6cbeecca571",
          "b_id":"OIP.GddkJOX8C37YLGHkUUGA-gHaE8",
          "media_fullsize":"\/\/s2.qwant.com\/thumbr\/0x0\/7\/d\/2abfc4ddce85c0f4fa06b88ef7650d972dc96740740f88551195a71d9dd602\/dog-in-hat-12.jpg?u=http%3A%2F%2Fcdn3-www.dogtime.com%2Fassets%2Fuploads%2F2016%2F03%2Fdog-in-hat-12.jpg&q=0&b=1&p=0&a=1",
          "thumb_type":"jpg",
          "count":54,
          "media_preview":"\/\/s2.qwant.com\/thumbr\/0x380\/5\/f\/ff1a3e05cc2e446ebbc0d5ab66c43ae358687ddc15742339125fbb5c3d4842\/dog-in-hat-12.jpg?u=http%3A%2F%2Fcdn3-www.dogtime.com%2Fassets%2Fuploads%2F2016%2F03%2Fdog-in-hat-12.jpg&q=0&b=1&p=0&a=1"
        },
        {
          "title":"Is It Really True That Dogs Dream? | Coops &amp; Cages Coops ...",
          "type":"image",
          "media":"https:\/\/publicdomainpictures.net\/pictures\/20000\/velka\/sleeping-dog-87129017161956E.jpg",
          "desc":"",
          "thumbnail":"\/\/s1.qwant.com\/thumbr\/299x200\/3\/b\/abd596bd77c616f5f7c69b8e6c5116d1db25967ea8f9022a7aedf9a82c3c92\/sleeping-dog-87129017161956E.jpg?u=https%3A%2F%2Fpublicdomainpictures.net%2Fpictures%2F20000%2Fvelka%2Fsleeping-dog-87129017161956E.jpg&q=0&b=1&p=0&a=0&b_id=OIP.QGsE5YGD0P53cnZZG-HnMQHaE8",
          "thumb_width":299,
          "thumb_height":200,
          "width":"1280",
          "height":"854",
          "size":"273647",
          "url":"https:\/\/www.coopsandcages.com.au\/blog\/really-true-dogs-dream\/",
          "_id":"b36583de058d55e9b9f71207c2fdd342",
          "b_id":"OIP.QGsE5YGD0P53cnZZG-HnMQHaE8",
          "media_fullsize":"\/\/s1.qwant.com\/thumbr\/0x0\/1\/c\/8582141eced79dad2c650db8f54b0e712edf227464ead52584e7239c416f31\/sleeping-dog-87129017161956E.jpg?u=https%3A%2F%2Fpublicdomainpictures.net%2Fpictures%2F20000%2Fvelka%2Fsleeping-dog-87129017161956E.jpg&q=0&b=1&p=0&a=1",
          "thumb_type":"jpg",
          "count":55,
          "media_preview":"\/\/s2.qwant.com\/thumbr\/0x380\/e\/f\/e99c0f88cbea501089edcff976d85e5c5cd05c464ceefb7fbe8d972127dd9a\/sleeping-dog-87129017161956E.jpg?u=https%3A%2F%2Fpublicdomainpictures.net%2Fpictures%2F20000%2Fvelka%2Fsleeping-dog-87129017161956E.jpg&q=0&b=1&p=0&a=1"
        },
        {
          "title":"Dogs Who Couldn't Be More Delighted That Spring Is Here",
          "type":"image",
          "media":"https:\/\/www.lifewithdogs.tv\/wp-content\/uploads\/2015\/03\/3.28.15-Dogs-in-Flowers5.jpg",
          "desc":"",
          "thumbnail":"\/\/s1.qwant.com\/thumbr\/224x200\/8\/9\/778a1a14061b2a7340dea48f46fa4699bb94e502772b38766ed954bf6f3498\/3.28.15-Dogs-in-Flowers5.jpg?u=https%3A%2F%2Fwww.lifewithdogs.tv%2Fwp-content%2Fuploads%2F2015%2F03%2F3.28.15-Dogs-in-Flowers5.jpg&q=0&b=1&p=0&a=0&b_id=OIP.vkIB4_Nken9eRAgr4AiMFAHaGl",
          "thumb_width":224,
          "thumb_height":200,
          "width":"960",
          "height":"854",
          "size":"203671",
          "url":"http:\/\/www.lifewithdogs.tv\/2015\/03\/dogs-who-couldnt-be-more-delighted-that-spring-is-here\/",
          "_id":"8882b952daea310029b4e0821a664270",
          "b_id":"OIP.vkIB4_Nken9eRAgr4AiMFAHaGl",
          "media_fullsize":"\/\/s2.qwant.com\/thumbr\/0x0\/d\/c\/60c6fbfe82d1ca286ca1e01fb00f46b8fa44482577239296da9209164785eb\/3.28.15-Dogs-in-Flowers5.jpg?u=https%3A%2F%2Fwww.lifewithdogs.tv%2Fwp-content%2Fuploads%2F2015%2F03%2F3.28.15-Dogs-in-Flowers5.jpg&q=0&b=1&p=0&a=1",
          "thumb_type":"jpg",
          "count":56,
          "media_preview":"\/\/s1.qwant.com\/thumbr\/0x380\/8\/1\/95cef5cfd9a728c30c599e97811cae0100f3d966ac1207f2d9587db3945983\/3.28.15-Dogs-in-Flowers5.jpg?u=https%3A%2F%2Fwww.lifewithdogs.tv%2Fwp-content%2Fuploads%2F2015%2F03%2F3.28.15-Dogs-in-Flowers5.jpg&q=0&b=1&p=0&a=1"
        },
        {
          "title":"Amazon.ca Dog Supplies: Dog Beds, Toys, Collars, Houses ...",
          "type":"image",
          "media":"https:\/\/images-na.ssl-images-amazon.com\/images\/G\/15\/img16\/pet-products\/content-grid\/981164_CA_pets_cg_mock_dogs_tile_feeding_1340x762.jpg",
          "desc":"",
          "thumbnail":"\/\/s1.qwant.com\/thumbr\/351x200\/8\/1\/059ff301b8b79b2b5ab0cd330697cbf9eb5ac4164ff3321904c847c693c7b1\/981164_CA_pets_cg_mock_dogs_tile_feeding_1340x762.jpg?u=https%3A%2F%2Fimages-na.ssl-images-amazon.com%2Fimages%2FG%2F15%2Fimg16%2Fpet-products%2Fcontent-grid%2F981164_CA_pets_cg_mock_dogs_tile_feeding_1340x762.jpg&q=0&b=1&p=0&a=0&b_id=OIP.Cue7YLG5ZvcotzsLVXwVfQHaEN",
          "thumb_width":351,
          "thumb_height":200,
          "width":"1340",
          "height":"762",
          "size":"164519",
          "url":"https:\/\/www.amazon.ca\/b?node=6292194011",
          "_id":"dc875a734299aad0ebb28f5097f1ebcd",
          "b_id":"OIP.Cue7YLG5ZvcotzsLVXwVfQHaEN",
          "media_fullsize":"\/\/s2.qwant.com\/thumbr\/0x0\/6\/7\/8d9d7b2d03bd24de44d0cf5b4fc4eb124790150c8ea2401f2eb8fecf61ae7a\/981164_CA_pets_cg_mock_dogs_tile_feeding_1340x762.jpg?u=https%3A%2F%2Fimages-na.ssl-images-amazon.com%2Fimages%2FG%2F15%2Fimg16%2Fpet-products%2Fcontent-grid%2F981164_CA_pets_cg_mock_dogs_tile_feeding_1340x762.jpg&q=0&b=1&p=0&a=1",
          "thumb_type":"jpg",
          "count":57,
          "media_preview":"\/\/s2.qwant.com\/thumbr\/0x380\/d\/9\/ac2e6190ad3fbd5e88cdb1fc756fa223c17e45e66af70dab5e5f910f3cf47e\/981164_CA_pets_cg_mock_dogs_tile_feeding_1340x762.jpg?u=https%3A%2F%2Fimages-na.ssl-images-amazon.com%2Fimages%2FG%2F15%2Fimg16%2Fpet-products%2Fcontent-grid%2F981164_CA_pets_cg_mock_dogs_tile_feeding_1340x762.jpg&q=0&b=1&p=0&a=1"
        },
        {
          "title":"Kangal Dog Wallpapers Backgrounds",
          "type":"image",
          "media":"http:\/\/wallpapersdsc.net\/wp-content\/uploads\/2017\/05\/Kangal-Dog-Wallpaper-.jpg",
          "desc":"",
          "thumbnail":"\/\/s1.qwant.com\/thumbr\/266x200\/9\/0\/63a20db7c5191d3f3d9d8c9821acafa910161168e6619c2e63c0bba7c81d28\/Kangal-Dog-Wallpaper-.jpg?u=http%3A%2F%2Fwallpapersdsc.net%2Fwp-content%2Fuploads%2F2017%2F05%2FKangal-Dog-Wallpaper-.jpg&q=0&b=1&p=0&a=0&b_id=OIP.SIGIVoBMQ0GMY7NEHxr8RwHaFj",
          "thumb_width":266,
          "thumb_height":200,
          "width":"1920",
          "height":"1440",
          "size":"596078",
          "url":"http:\/\/wallpapersdsc.net\/animals\/kangal-dog-70916.html",
          "_id":"699d4d1dc44a9977c1b4398f86929005",
          "b_id":"OIP.SIGIVoBMQ0GMY7NEHxr8RwHaFj",
          "media_fullsize":"\/\/s1.qwant.com\/thumbr\/0x0\/2\/8\/0db354decdfd2e9aa2947c325358b13a3c54b9d111506053717f54d1aa816c\/Kangal-Dog-Wallpaper-.jpg?u=http%3A%2F%2Fwallpapersdsc.net%2Fwp-content%2Fuploads%2F2017%2F05%2FKangal-Dog-Wallpaper-.jpg&q=0&b=1&p=0&a=1",
          "thumb_type":"jpg",
          "count":58,
          "media_preview":"\/\/s1.qwant.com\/thumbr\/0x380\/a\/0\/0b10c07768ba0c703b0baec5b5b517eb654cf2de1e4d9b3acadcb88c449c15\/Kangal-Dog-Wallpaper-.jpg?u=http%3A%2F%2Fwallpapersdsc.net%2Fwp-content%2Fuploads%2F2017%2F05%2FKangal-Dog-Wallpaper-.jpg&q=0&b=1&p=0&a=1"
        },
        {
          "title":"Free Images : white, puppy, cute, young, pets, dogs ...",
          "type":"image",
          "media":"https:\/\/c.pxhere.com\/photos\/a4\/a2\/animals_dogs_puppies_chihuahua-1120078.jpg!d",
          "desc":"",
          "thumbnail":"\/\/s1.qwant.com\/thumbr\/150x200\/3\/4\/c02c3d011b62ebbaaf52d07a76fcb3ea7c650d6c60acb2bf87ec05b9615a26\/animals_dogs_puppies_chihuahua-1120078.jpg!d.jpg?u=https%3A%2F%2Fc.pxhere.com%2Fphotos%2Fa4%2Fa2%2Fanimals_dogs_puppies_chihuahua-1120078.jpg%21d&q=0&b=1&p=0&a=0&b_id=OIP.SFljjWAMuQ_qArOUc4_RVwHaJ4",
          "thumb_width":150,
          "thumb_height":200,
          "width":"1200",
          "height":"1600",
          "size":"310830",
          "url":"https:\/\/pxhere.com\/en\/photo\/934976",
          "_id":"cf47a0031bcd8ce0ec9c9a3d1dbed89f",
          "b_id":"OIP.SFljjWAMuQ_qArOUc4_RVwHaJ4",
          "media_fullsize":"\/\/s1.qwant.com\/thumbr\/0x0\/9\/0\/c5ad6986010242add578be9bca917b33f77d14e77bfe13ce9a84bc42f8a1c6\/animals_dogs_puppies_chihuahua-1120078.jpg!d.jpg?u=https%3A%2F%2Fc.pxhere.com%2Fphotos%2Fa4%2Fa2%2Fanimals_dogs_puppies_chihuahua-1120078.jpg%21d&q=0&b=1&p=0&a=1",
          "thumb_type":"jpg!d",
          "count":59,
          "media_preview":"\/\/s1.qwant.com\/thumbr\/0x380\/0\/f\/0a5746180bf792ca561cd054cf10ca392acdf68a300440d824e4748def8057\/animals_dogs_puppies_chihuahua-1120078.jpg!d.jpg?u=https%3A%2F%2Fc.pxhere.com%2Fphotos%2Fa4%2Fa2%2Fanimals_dogs_puppies_chihuahua-1120078.jpg%21d&q=0&b=1&p=0&a=1"
        },
        {
          "title":"Dogs with Guns - Off-Topic - Comic Vine",
          "type":"image",
          "media":"https:\/\/static.comicvine.com\/uploads\/original\/6\/69951\/1997238-gedc0020.jpg",
          "desc":"",
          "thumbnail":"\/\/s2.qwant.com\/thumbr\/266x200\/d\/0\/6ce23d8cdacaa653a020956bdec148e45f6eeae53d21b6f5a49a17dd184ccf\/1997238-gedc0020.jpg?u=https%3A%2F%2Fstatic.comicvine.com%2Fuploads%2Foriginal%2F6%2F69951%2F1997238-gedc0020.jpg&q=0&b=1&p=0&a=0&b_id=OIP.jVqYfAg0wFOBJnKOCvEKzwHaFj",
          "thumb_width":266,
          "thumb_height":200,
          "width":"1024",
          "height":"768",
          "size":"87383",
          "url":"http:\/\/comicvine.gamespot.com\/forums\/off-topic-5\/dogs-with-guns-631622\/",
          "_id":"08437762d82d271a40a52aaee1c9e59f",
          "b_id":"OIP.jVqYfAg0wFOBJnKOCvEKzwHaFj",
          "media_fullsize":"\/\/s2.qwant.com\/thumbr\/0x0\/6\/6\/ca95975f4ed966cee315fad61853dbd9e9675bc6ce7ac9d888976ba782dcd0\/1997238-gedc0020.jpg?u=https%3A%2F%2Fstatic.comicvine.com%2Fuploads%2Foriginal%2F6%2F69951%2F1997238-gedc0020.jpg&q=0&b=1&p=0&a=1",
          "thumb_type":"jpg",
          "count":61,
          "media_preview":"\/\/s2.qwant.com\/thumbr\/0x380\/e\/2\/5659d01101836fac719d62e69a87fe89430453943d31bb10778ce8af622367\/1997238-gedc0020.jpg?u=https%3A%2F%2Fstatic.comicvine.com%2Fuploads%2Foriginal%2F6%2F69951%2F1997238-gedc0020.jpg&q=0&b=1&p=0&a=1"
        },
        {
          "title":"Utonagan Dog Breed Information, Buying Advice, Photos and ...",
          "type":"image",
          "media":"https:\/\/www.pets4homes.co.uk\/images\/breeds\/222\/large\/1667bf07961df7677eac986dba9f8724.jpg",
          "desc":"",
          "thumbnail":"\/\/s2.qwant.com\/thumbr\/275x200\/c\/3\/908bfc39f83f341eb521ef2b3d2479c1e20af1f02e4c279a1bad2db0612ffe\/1667bf07961df7677eac986dba9f8724.jpg?u=https%3A%2F%2Fwww.pets4homes.co.uk%2Fimages%2Fbreeds%2F222%2Flarge%2F1667bf07961df7677eac986dba9f8724.jpg&q=0&b=1&p=0&a=0&b_id=OIP.R6J315-Vi4YXfNKktGuigwHaFX",
          "thumb_width":275,
          "thumb_height":200,
          "width":"1280",
          "height":"928",
          "size":"91128",
          "url":"http:\/\/www.pets4homes.co.uk\/pets4homes\/home.nsf\/breedinfo\/utonagan",
          "_id":"2aac649b39a6501a4879f8303253703e",
          "b_id":"OIP.R6J315-Vi4YXfNKktGuigwHaFX",
          "media_fullsize":"\/\/s1.qwant.com\/thumbr\/0x0\/b\/0\/1a84dddd21f1854b1471d75b2f1865c0a89f90e66a033e091bd718a660c1a6\/1667bf07961df7677eac986dba9f8724.jpg?u=https%3A%2F%2Fwww.pets4homes.co.uk%2Fimages%2Fbreeds%2F222%2Flarge%2F1667bf07961df7677eac986dba9f8724.jpg&q=0&b=1&p=0&a=1",
          "thumb_type":"jpg",
          "count":62,
          "media_preview":"\/\/s1.qwant.com\/thumbr\/0x380\/b\/3\/84e1d67428def5da44eedff47f527c1b23c738b0da06a9920902cd6e2cc26b\/1667bf07961df7677eac986dba9f8724.jpg?u=https%3A%2F%2Fwww.pets4homes.co.uk%2Fimages%2Fbreeds%2F222%2Flarge%2F1667bf07961df7677eac986dba9f8724.jpg&q=0&b=1&p=0&a=1"
        },
        {
          "title":"Bleeding Under the Skin in Dogs - Symptoms, Causes ...",
          "type":"image",
          "media":"https:\/\/images.wagwalkingweb.com\/media\/articles\/dog\/bleeding-under-skin\/bleeding-under-skin.jpg",
          "desc":"",
          "thumbnail":"\/\/s1.qwant.com\/thumbr\/300x200\/8\/5\/c97c44ff41306e4d2f7354fa3dfeb56d8bc6fd441a67f5002f262e9b40850b\/bleeding-under-skin.jpg?u=https%3A%2F%2Fimages.wagwalkingweb.com%2Fmedia%2Farticles%2Fdog%2Fbleeding-under-skin%2Fbleeding-under-skin.jpg&q=0&b=1&p=0&a=0&b_id=OIP.HuZ-WmyV0gu79U4EYnWujQHaE8",
          "thumb_width":300,
          "thumb_height":200,
          "width":"2100",
          "height":"1400",
          "size":"343308",
          "url":"https:\/\/www.vetary.com\/dog\/condition\/bleeding-under-skin",
          "_id":"702e294195d5cbcae70449f1c0e95490",
          "b_id":"OIP.HuZ-WmyV0gu79U4EYnWujQHaE8",
          "media_fullsize":"\/\/s1.qwant.com\/thumbr\/0x0\/1\/0\/e16445c6f58ec342b9eed4d3dd3275abf60076b143dd536a9e7a52e3025d3b\/bleeding-under-skin.jpg?u=https%3A%2F%2Fimages.wagwalkingweb.com%2Fmedia%2Farticles%2Fdog%2Fbleeding-under-skin%2Fbleeding-under-skin.jpg&q=0&b=1&p=0&a=1",
          "thumb_type":"jpg",
          "count":63,
          "media_preview":"\/\/s1.qwant.com\/thumbr\/0x380\/9\/7\/c95c2fe8a048021c830baf11580cd62468a4c5f32e57da7ee0cd9666ed8ff1\/bleeding-under-skin.jpg?u=https%3A%2F%2Fimages.wagwalkingweb.com%2Fmedia%2Farticles%2Fdog%2Fbleeding-under-skin%2Fbleeding-under-skin.jpg&q=0&b=1&p=0&a=1"
        },
        {
          "title":"MICHAEL KNIGHT - Villalobos Rescue Center",
          "type":"image",
          "media":"http:\/\/www.vrcpitbull.com\/wp-content\/uploads\/2013\/08\/mk5.jpg",
          "desc":"",
          "thumbnail":"\/\/s1.qwant.com\/thumbr\/299x200\/3\/5\/99ad905c1975beb1ef470218493421c6fe56f3a471e6989953e770151c5069\/mk5.jpg?u=http%3A%2F%2Fwww.vrcpitbull.com%2Fwp-content%2Fuploads%2F2013%2F08%2Fmk5.jpg&q=0&b=1&p=0&a=0&b_id=OIP.BDCNCnIxn-BpML8MgYZeegHaE8",
          "thumb_width":299,
          "thumb_height":200,
          "width":"1600",
          "height":"1067",
          "size":"1255184",
          "url":"http:\/\/www.vrcpitbull.com\/dogs\/michael-knight\/",
          "_id":"cf47869b9efa2048839aba7e2ab60bbb",
          "b_id":"OIP.BDCNCnIxn-BpML8MgYZeegHaE8",
          "media_fullsize":"\/\/s2.qwant.com\/thumbr\/0x0\/4\/e\/21be08489b32fb589139649a2750d527f9de5a56749d5a21de323549ed9f8e\/mk5.jpg?u=http%3A%2F%2Fwww.vrcpitbull.com%2Fwp-content%2Fuploads%2F2013%2F08%2Fmk5.jpg&q=0&b=1&p=0&a=1",
          "thumb_type":"jpg",
          "count":64,
          "media_preview":"\/\/s2.qwant.com\/thumbr\/0x380\/7\/6\/fa2dffd75d6a1c10fd00512d51418316bcfd2021a0495bf3b6620440ac22fe\/mk5.jpg?u=http%3A%2F%2Fwww.vrcpitbull.com%2Fwp-content%2Fuploads%2F2013%2F08%2Fmk5.jpg&q=0&b=1&p=0&a=1"
        },
        {
          "title":"Hwange National Park and the Survival of the African ...",
          "type":"image",
          "media":"https:\/\/i1.wp.com\/www.wayfaringviews.com\/wp-content\/uploads\/2016\/06\/Four_Dogs.jpg?resize=1920%2C1278&ssl=1",
          "desc":"",
          "thumbnail":"\/\/s2.qwant.com\/thumbr\/300x200\/6\/3\/3b5f4c437a0e71c46295ea4d6200d95e6705e871fa93ca86da788646c65cc7\/Four_Dogs.jpg?u=https%3A%2F%2Fi1.wp.com%2Fwww.wayfaringviews.com%2Fwp-content%2Fuploads%2F2016%2F06%2FFour_Dogs.jpg%3Fresize%3D1920%252C1278%26ssl%3D1&q=0&b=1&p=0&a=0&b_id=OIP.0ttgX4uM98QZFG9ZcKHjQwHaE7",
          "thumb_width":300,
          "thumb_height":200,
          "width":"1920",
          "height":"1278",
          "size":"131870",
          "url":"https:\/\/wayfaringviews.com\/hwange-national-park-african-painted-dog\/",
          "_id":"c9fb09eb3d25f2bb94396a0887391efd",
          "b_id":"OIP.0ttgX4uM98QZFG9ZcKHjQwHaE7",
          "media_fullsize":"\/\/s1.qwant.com\/thumbr\/0x0\/9\/6\/e96b9d40a7737c4542c2929bd5b5015b0dde6e178b6bff36e003e0d3e55c18\/Four_Dogs.jpg?u=https%3A%2F%2Fi1.wp.com%2Fwww.wayfaringviews.com%2Fwp-content%2Fuploads%2F2016%2F06%2FFour_Dogs.jpg%3Fresize%3D1920%252C1278%26ssl%3D1&q=0&b=1&p=0&a=1",
          "thumb_type":"jpg",
          "count":65,
          "media_preview":"\/\/s2.qwant.com\/thumbr\/0x380\/5\/8\/c5a21126361777712d34bbf10463996e02bd2de226a0935a4ed3fd158917f2\/Four_Dogs.jpg?u=https%3A%2F%2Fi1.wp.com%2Fwww.wayfaringviews.com%2Fwp-content%2Fuploads%2F2016%2F06%2FFour_Dogs.jpg%3Fresize%3D1920%252C1278%26ssl%3D1&q=0&b=1&p=0&a=1"
        },
        {
          "title":"Dogs take flight in hilarious photos - TODAY.com",
          "type":"image",
          "media":"https:\/\/media3.s-nbcnews.com\/j\/MSNBC\/Components\/Slideshows\/_production\/TODAY-ready\/ss-141123-flying-dogs\/ss-141123-flying-dogs-tease.today-ss-slide-desktop.jpg",
          "desc":"",
          "thumbnail":"\/\/s2.qwant.com\/thumbr\/355x200\/6\/a\/8d54a1ccdbd684c22d0f7bdbe159cea3c8b4bcbd0cb5fb9d8169c5fb029173\/ss-141123-flying-dogs-tease.today-ss-slide-desktop.jpg?u=https%3A%2F%2Fmedia3.s-nbcnews.com%2Fj%2FMSNBC%2FComponents%2FSlideshows%2F_production%2FTODAY-ready%2Fss-141123-flying-dogs%2Fss-141123-flying-dogs-tease.today-ss-slide-desktop.jpg&q=0&b=1&p=0&a=0&b_id=OIP.L7ggNAIftI34AV2qjT4t0QHaEK",
          "thumb_width":355,
          "thumb_height":200,
          "width":"1920",
          "height":"1080",
          "size":"96576",
          "url":"http:\/\/www.today.com\/pets\/dogs-take-flight-hilarious-photos-1D80324002",
          "_id":"be2679f0ebb65517437bcfbb9d087593",
          "b_id":"OIP.L7ggNAIftI34AV2qjT4t0QHaEK",
          "media_fullsize":"\/\/s2.qwant.com\/thumbr\/0x0\/d\/a\/76142c86c3087a1dbf689cc01b3780d682add8e986fc70af1d7880fb0380f7\/ss-141123-flying-dogs-tease.today-ss-slide-desktop.jpg?u=https%3A%2F%2Fmedia3.s-nbcnews.com%2Fj%2FMSNBC%2FComponents%2FSlideshows%2F_production%2FTODAY-ready%2Fss-141123-flying-dogs%2Fss-141123-flying-dogs-tease.today-ss-slide-desktop.jpg&q=0&b=1&p=0&a=1",
          "thumb_type":"jpg",
          "count":67,
          "media_preview":"\/\/s2.qwant.com\/thumbr\/0x380\/4\/7\/6260b3c33bdb48222b0fea55c5a65d00a96a1cbddcf6ec3b89f9eca5781b33\/ss-141123-flying-dogs-tease.today-ss-slide-desktop.jpg?u=https%3A%2F%2Fmedia3.s-nbcnews.com%2Fj%2FMSNBC%2FComponents%2FSlideshows%2F_production%2FTODAY-ready%2Fss-141123-flying-dogs%2Fss-141123-flying-dogs-tease.today-ss-slide-desktop.jpg&q=0&b=1&p=0&a=1"
        },
        {
          "title":"Giant Schnauzer Dog Breed Information, Buying Advice ...",
          "type":"image",
          "media":"http:\/\/www.pets4homes.co.uk\/images\/breeds\/47\/large\/5d7de6a74648c280d10fbc7da666bab8.jpg",
          "desc":"",
          "thumbnail":"\/\/s2.qwant.com\/thumbr\/300x200\/5\/e\/19e65b58dbab7053368d2348b2ecd16ccb49f06dd5337a9c609889eed0dca6\/5d7de6a74648c280d10fbc7da666bab8.jpg?u=http%3A%2F%2Fwww.pets4homes.co.uk%2Fimages%2Fbreeds%2F47%2Flarge%2F5d7de6a74648c280d10fbc7da666bab8.jpg&q=0&b=1&p=0&a=0&b_id=OIP.ssdcH86uGedoY3QvF0FXcQHaE7",
          "thumb_width":300,
          "thumb_height":200,
          "width":"1280",
          "height":"853",
          "size":"179913",
          "url":"http:\/\/www.pets4homes.co.uk\/pets4homes\/home.nsf\/breedinfo\/giantschnauzer",
          "_id":"0062ae391df86b55fd1d3b495b3b95ee",
          "b_id":"OIP.ssdcH86uGedoY3QvF0FXcQHaE7",
          "media_fullsize":"\/\/s2.qwant.com\/thumbr\/0x0\/e\/a\/947a4e723e428b0add49bee3669b0250ba0f57b664e2ffae15ab4460407e02\/5d7de6a74648c280d10fbc7da666bab8.jpg?u=http%3A%2F%2Fwww.pets4homes.co.uk%2Fimages%2Fbreeds%2F47%2Flarge%2F5d7de6a74648c280d10fbc7da666bab8.jpg&q=0&b=1&p=0&a=1",
          "thumb_type":"jpg",
          "count":68,
          "media_preview":"\/\/s1.qwant.com\/thumbr\/0x380\/1\/9\/ff3c4cbcac35f8740153178980f2630b6d852375ac1c68d4ad0473351470db\/5d7de6a74648c280d10fbc7da666bab8.jpg?u=http%3A%2F%2Fwww.pets4homes.co.uk%2Fimages%2Fbreeds%2F47%2Flarge%2F5d7de6a74648c280d10fbc7da666bab8.jpg&q=0&b=1&p=0&a=1"
        },
        {
          "title":"Australian Shepherd Dog Breed Information, Buying Advice ...",
          "type":"image",
          "media":"http:\/\/www.pets4homes.co.uk\/images\/breeds\/191\/large\/b021b93c0542ecc23ce5c702222424f3.jpg",
          "desc":"",
          "thumbnail":"\/\/s2.qwant.com\/thumbr\/300x200\/d\/5\/538d434cc440b117f0d8673579c91f65f01fe4a17d29406f823524af69797b\/b021b93c0542ecc23ce5c702222424f3.jpg?u=http%3A%2F%2Fwww.pets4homes.co.uk%2Fimages%2Fbreeds%2F191%2Flarge%2Fb021b93c0542ecc23ce5c702222424f3.jpg&q=0&b=1&p=0&a=0&b_id=OIP.5_sWwUh_Vi7GmEWHh_QclAHaE7",
          "thumb_width":300,
          "thumb_height":200,
          "width":"1280",
          "height":"853",
          "size":"93617",
          "url":"http:\/\/www.pets4homes.co.uk\/pets4homes\/home.nsf\/breedinfo\/australianshepherd",
          "_id":"309b52cb114c9e833805b5496bb673c2",
          "b_id":"OIP.5_sWwUh_Vi7GmEWHh_QclAHaE7",
          "media_fullsize":"\/\/s2.qwant.com\/thumbr\/0x0\/c\/1\/ee47bed6b329748c24ccfc312903688ff1857311ad0580b25f5f5c837ecd63\/b021b93c0542ecc23ce5c702222424f3.jpg?u=http%3A%2F%2Fwww.pets4homes.co.uk%2Fimages%2Fbreeds%2F191%2Flarge%2Fb021b93c0542ecc23ce5c702222424f3.jpg&q=0&b=1&p=0&a=1",
          "thumb_type":"jpg",
          "count":69,
          "media_preview":"\/\/s1.qwant.com\/thumbr\/0x380\/b\/c\/d177051cd44098955626d174d4d4c0bde1dac8860ed01ea04a5e4a47928ec0\/b021b93c0542ecc23ce5c702222424f3.jpg?u=http%3A%2F%2Fwww.pets4homes.co.uk%2Fimages%2Fbreeds%2F191%2Flarge%2Fb021b93c0542ecc23ce5c702222424f3.jpg&q=0&b=1&p=0&a=1"
        },
        {
          "title":"Anatolian Shepherd - Dogs breeds | Pets",
          "type":"image",
          "media":"https:\/\/www.mascotarios.org\/wp-content\/gallery\/pastordeanatolia\/pastordeanatolia9.jpg",
          "desc":"",
          "thumbnail":"\/\/s1.qwant.com\/thumbr\/266x200\/a\/7\/c192932b1721458e9010a426cb8c3205516b319f6f8ccd6926d7980d15fea5\/pastordeanatolia9.jpg?u=https%3A%2F%2Fwww.mascotarios.org%2Fwp-content%2Fgallery%2Fpastordeanatolia%2Fpastordeanatolia9.jpg&q=0&b=1&p=0&a=0&b_id=OIP.lp90TomzkBBUi4554K7iMAHaFj",
          "thumb_width":266,
          "thumb_height":200,
          "width":"1024",
          "height":"768",
          "size":"244258",
          "url":"https:\/\/www.mascotarios.org\/en\/pastor-de-anatolia\/",
          "_id":"c4ff412c349e618174d193772dc60560",
          "b_id":"OIP.lp90TomzkBBUi4554K7iMAHaFj",
          "media_fullsize":"\/\/s2.qwant.com\/thumbr\/0x0\/e\/a\/e21e135ef63eb66bcfa8c75becd427b28d47d354ae3a31df4eb425da4dbb5f\/pastordeanatolia9.jpg?u=https%3A%2F%2Fwww.mascotarios.org%2Fwp-content%2Fgallery%2Fpastordeanatolia%2Fpastordeanatolia9.jpg&q=0&b=1&p=0&a=1",
          "thumb_type":"jpg",
          "count":70,
          "media_preview":"\/\/s2.qwant.com\/thumbr\/0x380\/6\/c\/eb7ffdfdf0b8f9e01a3bc7fcd6d49942a17743bd1b4b8f1bc71f1b43cada7d\/pastordeanatolia9.jpg?u=https%3A%2F%2Fwww.mascotarios.org%2Fwp-content%2Fgallery%2Fpastordeanatolia%2Fpastordeanatolia9.jpg&q=0&b=1&p=0&a=1"
        },
        {
          "title":"Spanish Mastiff Info, Puppies, Training, Pictures, Temperament",
          "type":"image",
          "media":"http:\/\/www.101dogbreeds.com\/wp-content\/uploads\/2014\/10\/Spanish-Mastiff-Puppy-Images.jpg",
          "desc":"",
          "thumbnail":"\/\/s2.qwant.com\/thumbr\/200x200\/c\/9\/08371497644bd38b839fae67a4aecdf33e58a61cc3de481a40c71bf25bf27a\/Spanish-Mastiff-Puppy-Images.jpg?u=http%3A%2F%2Fwww.101dogbreeds.com%2Fwp-content%2Fuploads%2F2014%2F10%2FSpanish-Mastiff-Puppy-Images.jpg&q=0&b=1&p=0&a=0&b_id=OIP.bFf4qZHgiOhof-1C-ttt7QHaHZ",
          "thumb_width":200,
          "thumb_height":200,
          "width":"1600",
          "height":"1598",
          "size":"349203",
          "url":"http:\/\/www.101dogbreeds.com\/spanish-mastiff.asp",
          "_id":"93c6f3f1c0ae2ea72cfcd62cdfe159e0",
          "b_id":"OIP.bFf4qZHgiOhof-1C-ttt7QHaHZ",
          "media_fullsize":"\/\/s1.qwant.com\/thumbr\/0x0\/2\/f\/2a6d59fb8d2653059b01860d1d18bd568aa02ec8bd82d5693f64cfb83e35df\/Spanish-Mastiff-Puppy-Images.jpg?u=http%3A%2F%2Fwww.101dogbreeds.com%2Fwp-content%2Fuploads%2F2014%2F10%2FSpanish-Mastiff-Puppy-Images.jpg&q=0&b=1&p=0&a=1",
          "thumb_type":"jpg",
          "count":71,
          "media_preview":"\/\/s2.qwant.com\/thumbr\/0x380\/c\/6\/c872631ace5dd5883ed9e94be1fb26ef8ff04c32bfdd75a474811ab5e8a7f8\/Spanish-Mastiff-Puppy-Images.jpg?u=http%3A%2F%2Fwww.101dogbreeds.com%2Fwp-content%2Fuploads%2F2014%2F10%2FSpanish-Mastiff-Puppy-Images.jpg&q=0&b=1&p=0&a=1"
        },
        {
          "title":"Can dogs eat cheese? | Pets4Homes",
          "type":"image",
          "media":"https:\/\/www.pets4homes.co.uk\/images\/articles\/3267\/large\/can-dogs-eat-cheese-561ceb68f0502.jpg",
          "desc":"",
          "thumbnail":"\/\/s2.qwant.com\/thumbr\/352x200\/c\/c\/bf04b0c0c5c4a31b015e76455cc339b3b7397b66be8c9e0f460d8e42e29483\/can-dogs-eat-cheese-561ceb68f0502.jpg?u=https%3A%2F%2Fwww.pets4homes.co.uk%2Fimages%2Farticles%2F3267%2Flarge%2Fcan-dogs-eat-cheese-561ceb68f0502.jpg&q=0&b=1&p=0&a=0&b_id=OIP.vES1xF2I1u9ISGWemwVn8QHaEN",
          "thumb_width":352,
          "thumb_height":200,
          "width":"1280",
          "height":"727",
          "size":"64547",
          "url":"https:\/\/www.pets4homes.co.uk\/pet-advice\/can-dogs-eat-cheese.html",
          "_id":"d48d8e185811c9533baa45214e37eee8",
          "b_id":"OIP.vES1xF2I1u9ISGWemwVn8QHaEN",
          "media_fullsize":"\/\/s2.qwant.com\/thumbr\/0x0\/f\/4\/a47e0f3180f6d8d7bc191bd752920dcc9cd65a4397539de11fe3766ab5d80a\/can-dogs-eat-cheese-561ceb68f0502.jpg?u=https%3A%2F%2Fwww.pets4homes.co.uk%2Fimages%2Farticles%2F3267%2Flarge%2Fcan-dogs-eat-cheese-561ceb68f0502.jpg&q=0&b=1&p=0&a=1",
          "thumb_type":"jpg",
          "count":72,
          "media_preview":"\/\/s1.qwant.com\/thumbr\/0x380\/a\/5\/29db5b5fd6f673c8b64850fff2ff14d8e0b1879c8a9b07081e0f2b83271edc\/can-dogs-eat-cheese-561ceb68f0502.jpg?u=https%3A%2F%2Fwww.pets4homes.co.uk%2Fimages%2Farticles%2F3267%2Flarge%2Fcan-dogs-eat-cheese-561ceb68f0502.jpg&q=0&b=1&p=0&a=1"
        },
        {
          "title":"Special Dogs",
          "type":"image",
          "media":"http:\/\/secondhandmutts.org\/wp-content\/uploads\/2013\/02\/Miracle-23.jpg",
          "desc":"",
          "thumbnail":"\/\/s2.qwant.com\/thumbr\/133x200\/e\/0\/16ce738383e6b5888d2a5be0e6b04c4f271478f6f8fab48277c4d9d3a54668\/Miracle-23.jpg?u=http%3A%2F%2Fsecondhandmutts.org%2Fwp-content%2Fuploads%2F2013%2F02%2FMiracle-23.jpg&q=0&b=1&p=0&a=0&b_id=OIP.5ozQyijH1Mvkz5UbTSv22wHaLH",
          "thumb_width":133,
          "thumb_height":200,
          "width":"2400",
          "height":"3600",
          "size":"1813370",
          "url":"http:\/\/secondhandmutts.org\/donate\/dogs-needing-funding\/",
          "_id":"53f090aa35f5532cee90bac5e899e99e",
          "b_id":"OIP.5ozQyijH1Mvkz5UbTSv22wHaLH",
          "media_fullsize":"\/\/s1.qwant.com\/thumbr\/0x0\/8\/d\/dd0a3c531d1a57c49c5bcc15950e80de34006f68b57acc4c5d1bc81b447b5a\/Miracle-23.jpg?u=http%3A%2F%2Fsecondhandmutts.org%2Fwp-content%2Fuploads%2F2013%2F02%2FMiracle-23.jpg&q=0&b=1&p=0&a=1",
          "thumb_type":"jpg",
          "count":73,
          "media_preview":"\/\/s1.qwant.com\/thumbr\/0x380\/b\/5\/14346c1b9b79eb72a71fa4388f31f6dc9b1d7888e5e64beedeed6cf0ca855b\/Miracle-23.jpg?u=http%3A%2F%2Fsecondhandmutts.org%2Fwp-content%2Fuploads%2F2013%2F02%2FMiracle-23.jpg&q=0&b=1&p=0&a=1"
        },
        {
          "title":"Bichon Bolognese - Dogs breeds | Pets",
          "type":"image",
          "media":"https:\/\/www.mascotarios.org\/wp-content\/gallery\/bolognese\/bolognese6.jpg",
          "desc":"",
          "thumbnail":"\/\/s2.qwant.com\/thumbr\/210x200\/6\/5\/3b277cf9aeb71056420dffb767a44060671bfc416c1f1c8f88e261f647d8ac\/bolognese6.jpg?u=https%3A%2F%2Fwww.mascotarios.org%2Fwp-content%2Fgallery%2Fbolognese%2Fbolognese6.jpg&q=0&b=1&p=0&a=0&b_id=OIP.BXr8gaWOY_qZrejvsl1gpAHaHC",
          "thumb_width":210,
          "thumb_height":200,
          "width":"900",
          "height":"855",
          "size":"52849",
          "url":"https:\/\/www.mascotarios.org\/en\/bichon-bolones\/",
          "_id":"d902c0215f4cd7d90ff9cf2bced4bba4",
          "b_id":"OIP.BXr8gaWOY_qZrejvsl1gpAHaHC",
          "media_fullsize":"\/\/s1.qwant.com\/thumbr\/0x0\/2\/c\/6407c5e871689542198732fcdceb81aae753555e15c00125ee22deab1210ed\/bolognese6.jpg?u=https%3A%2F%2Fwww.mascotarios.org%2Fwp-content%2Fgallery%2Fbolognese%2Fbolognese6.jpg&q=0&b=1&p=0&a=1",
          "thumb_type":"jpg",
          "count":74,
          "media_preview":"\/\/s1.qwant.com\/thumbr\/0x380\/3\/5\/e6fc8ccdd8070ab1afc4a6edfe5a21c49f73d4f7a602420623deb3e20f1518\/bolognese6.jpg?u=https%3A%2F%2Fwww.mascotarios.org%2Fwp-content%2Fgallery%2Fbolognese%2Fbolognese6.jpg&q=0&b=1&p=0&a=1"
        },
        {
          "title":"Holland's Midnight Miss Demeanor &quot;Jett&quot; | Boxer family and ...",
          "type":"image",
          "media":"https:\/\/s-media-cache-ak0.pinimg.com\/736x\/b4\/6b\/1e\/b46b1e1e5b9e9e4b7a9a82bd8f01943d--boxer-tigrado-brindle-boxer.jpg",
          "desc":"",
          "thumbnail":"\/\/s1.qwant.com\/thumbr\/143x200\/2\/6\/adb23203e3933135e5be56e71c4a61774646100836b253ccf5e85bcecf6b8c\/b46b1e1e5b9e9e4b7a9a82bd8f01943d--boxer-tigrado-brindle-boxer.jpg?u=https%3A%2F%2Fs-media-cache-ak0.pinimg.com%2F736x%2Fb4%2F6b%2F1e%2Fb46b1e1e5b9e9e4b7a9a82bd8f01943d--boxer-tigrado-brindle-boxer.jpg&q=0&b=1&p=0&a=0&b_id=OIP.6A__toBZKHDHpfTTJts--QHaKW",
          "thumb_width":143,
          "thumb_height":200,
          "width":"736",
          "height":"1029",
          "size":"125266",
          "url":"https:\/\/www.pinterest.com\/pin\/165788830009715949\/",
          "_id":"72a435bf5d865e22ff7898a5d136101b",
          "b_id":"OIP.6A__toBZKHDHpfTTJts--QHaKW",
          "media_fullsize":"\/\/s2.qwant.com\/thumbr\/0x0\/7\/0\/58a8eaf8b02da2d40edc5c02bcbad888cb2202dac059169da77399be348d77\/b46b1e1e5b9e9e4b7a9a82bd8f01943d--boxer-tigrado-brindle-boxer.jpg?u=https%3A%2F%2Fs-media-cache-ak0.pinimg.com%2F736x%2Fb4%2F6b%2F1e%2Fb46b1e1e5b9e9e4b7a9a82bd8f01943d--boxer-tigrado-brindle-boxer.jpg&q=0&b=1&p=0&a=1",
          "thumb_type":"jpg",
          "count":75,
          "media_preview":"\/\/s2.qwant.com\/thumbr\/0x380\/5\/8\/0e3962f574d11d189917e0ae32fff5246279b3232ab8c5145fd5d4046fd74f\/b46b1e1e5b9e9e4b7a9a82bd8f01943d--boxer-tigrado-brindle-boxer.jpg?u=https%3A%2F%2Fs-media-cache-ak0.pinimg.com%2F736x%2Fb4%2F6b%2F1e%2Fb46b1e1e5b9e9e4b7a9a82bd8f01943d--boxer-tigrado-brindle-boxer.jpg&q=0&b=1&p=0&a=1"
        },
        {
          "title":"Hungarian Vizsla Dog Breed Information, Buying Advice ...",
          "type":"image",
          "media":"https:\/\/www.pets4homes.co.uk\/images\/breeds\/88\/large\/abaf7563b8e41cdfb0bccd90cc37187a.jpg",
          "desc":"",
          "thumbnail":"\/\/s2.qwant.com\/thumbr\/300x200\/6\/7\/572501676a74b00accc160339400fbc499db10b6f0145f51c3ff0e992e2cb8\/abaf7563b8e41cdfb0bccd90cc37187a.jpg?u=https%3A%2F%2Fwww.pets4homes.co.uk%2Fimages%2Fbreeds%2F88%2Flarge%2Fabaf7563b8e41cdfb0bccd90cc37187a.jpg&q=0&b=1&p=0&a=0&b_id=OIP.u9YQlYvP1hm-zprz0gH9dAHaE7",
          "thumb_width":300,
          "thumb_height":200,
          "width":"1280",
          "height":"853",
          "size":"116955",
          "url":"https:\/\/www.pets4homes.co.uk\/pets4homes\/home.nsf\/breedinfo\/hungarianvizsla",
          "_id":"614e2b8c51dca6a0afe6503025ed4d43",
          "b_id":"OIP.u9YQlYvP1hm-zprz0gH9dAHaE7",
          "media_fullsize":"\/\/s1.qwant.com\/thumbr\/0x0\/0\/6\/28491fedb02acaf01eef1165ac3c333d70e810b6df8a83cf453f44cb790d05\/abaf7563b8e41cdfb0bccd90cc37187a.jpg?u=https%3A%2F%2Fwww.pets4homes.co.uk%2Fimages%2Fbreeds%2F88%2Flarge%2Fabaf7563b8e41cdfb0bccd90cc37187a.jpg&q=0&b=1&p=0&a=1",
          "thumb_type":"jpg",
          "count":76,
          "media_preview":"\/\/s2.qwant.com\/thumbr\/0x380\/7\/c\/58d0c9a706213ba6a7cd49716e58d4d513c1d8238ff5079021a633e467daca\/abaf7563b8e41cdfb0bccd90cc37187a.jpg?u=https%3A%2F%2Fwww.pets4homes.co.uk%2Fimages%2Fbreeds%2F88%2Flarge%2Fabaf7563b8e41cdfb0bccd90cc37187a.jpg&q=0&b=1&p=0&a=1"
        },
        {
          "title":"Dogs may have been domesticated more than once | Science ...",
          "type":"image",
          "media":"http:\/\/www.sciencemag.org\/sites\/default\/files\/styles\/article_main_large\/public\/images\/60603W_Dogs.jpg?itok=wfFTNLPN",
          "desc":"",
          "thumbnail":"\/\/s2.qwant.com\/thumbr\/355x200\/d\/0\/617d91bddb08dac4edc1d48ce817125ce11fe6593749b72e92b722bc11d0dc\/60603W_Dogs.jpg?u=http%3A%2F%2Fwww.sciencemag.org%2Fsites%2Fdefault%2Ffiles%2Fstyles%2Farticle_main_large%2Fpublic%2Fimages%2F60603W_Dogs.jpg%3Fitok%3DwfFTNLPN&q=0&b=1&p=0&a=0&b_id=OIP.U-9RqFdsplGWVhLzD697QgHaEK",
          "thumb_width":355,
          "thumb_height":200,
          "width":"1280",
          "height":"720",
          "size":"270748",
          "url":"https:\/\/www.sciencemag.org\/news\/2016\/06\/dogs-may-have-been-domesticated-more-once",
          "_id":"f64123d0e2d45d6aa91a950ccb0f875f",
          "b_id":"OIP.U-9RqFdsplGWVhLzD697QgHaEK",
          "media_fullsize":"\/\/s2.qwant.com\/thumbr\/0x0\/f\/9\/0cfe6bebfeb3bb186731f7e21318ac1f62364498778f106a1c84d1f3d66ea0\/60603W_Dogs.jpg?u=http%3A%2F%2Fwww.sciencemag.org%2Fsites%2Fdefault%2Ffiles%2Fstyles%2Farticle_main_large%2Fpublic%2Fimages%2F60603W_Dogs.jpg%3Fitok%3DwfFTNLPN&q=0&b=1&p=0&a=1",
          "thumb_type":"jpg",
          "count":77,
          "media_preview":"\/\/s2.qwant.com\/thumbr\/0x380\/c\/4\/5026a079789d6c2c48f7633744b235c9b4953764c6e90158f55b4681cbf69f\/60603W_Dogs.jpg?u=http%3A%2F%2Fwww.sciencemag.org%2Fsites%2Fdefault%2Ffiles%2Fstyles%2Farticle_main_large%2Fpublic%2Fimages%2F60603W_Dogs.jpg%3Fitok%3DwfFTNLPN&q=0&b=1&p=0&a=1"
        },
        {
          "title":"Maltese Dog Breed Information, Buying Advice, Photos and ...",
          "type":"image",
          "media":"https:\/\/www.pets4homes.co.uk\/images\/breeds\/59\/large\/0f97db75db2969f0eb8374626e074365.jpg",
          "desc":"",
          "thumbnail":"\/\/s2.qwant.com\/thumbr\/280x200\/5\/9\/0ff5b31da3f6c67a20f6a24292607e9859d6f3f8b85fc8e1083425c43233fb\/0f97db75db2969f0eb8374626e074365.jpg?u=https%3A%2F%2Fwww.pets4homes.co.uk%2Fimages%2Fbreeds%2F59%2Flarge%2F0f97db75db2969f0eb8374626e074365.jpg&q=0&b=1&p=0&a=0&b_id=OIP.ZvXIDhGU0CfcNWt9wSDrdwHaFR",
          "thumb_width":280,
          "thumb_height":200,
          "width":"1280",
          "height":"912",
          "size":"80205",
          "url":"https:\/\/www.pets4homes.co.uk\/pets4homes\/home.nsf\/breedinfo\/maltese",
          "_id":"457360d1846c73cbb5677bc5303f3dbf",
          "b_id":"OIP.ZvXIDhGU0CfcNWt9wSDrdwHaFR",
          "media_fullsize":"\/\/s1.qwant.com\/thumbr\/0x0\/3\/1\/424250e7ac3eba8568123da0801d1e3abcd1e05690c73cc8039c2f3589ea83\/0f97db75db2969f0eb8374626e074365.jpg?u=https%3A%2F%2Fwww.pets4homes.co.uk%2Fimages%2Fbreeds%2F59%2Flarge%2F0f97db75db2969f0eb8374626e074365.jpg&q=0&b=1&p=0&a=1",
          "thumb_type":"jpg",
          "count":78,
          "media_preview":"\/\/s1.qwant.com\/thumbr\/0x380\/0\/7\/3a4ef251ec77a085fd5a996d05214f91a327d97b30a923443cb11f1df14a89\/0f97db75db2969f0eb8374626e074365.jpg?u=https%3A%2F%2Fwww.pets4homes.co.uk%2Fimages%2Fbreeds%2F59%2Flarge%2F0f97db75db2969f0eb8374626e074365.jpg&q=0&b=1&p=0&a=1"
        },
        {
          "title":"Why Do Dogs Eat Poop? | Healthy Paws",
          "type":"image",
          "media":"https:\/\/www.healthypawspetinsurance.com\/blog\/wp-content\/uploads\/guilty_cute_dog_puppy_trouble_accident.jpg",
          "desc":"",
          "thumbnail":"\/\/s2.qwant.com\/thumbr\/299x200\/f\/1\/27dd7cd7e9afcd06a282a56fa30f0dccdafd2cf61c5d8dd126996b1695da17\/guilty_cute_dog_puppy_trouble_accident.jpg?u=https%3A%2F%2Fwww.healthypawspetinsurance.com%2Fblog%2Fwp-content%2Fuploads%2Fguilty_cute_dog_puppy_trouble_accident.jpg&q=0&b=1&p=0&a=0&b_id=OIP.H6CZmyaTpAjQJ0VERbm-HAHaE8",
          "thumb_width":299,
          "thumb_height":200,
          "width":"1280",
          "height":"856",
          "size":"336000",
          "url":"http:\/\/www.healthypawspetinsurance.com\/blog\/2015\/07\/20\/why-do-dogs-eat-poop-2\/",
          "_id":"07ddd59b0234d523a48858aceed42d5e",
          "b_id":"OIP.H6CZmyaTpAjQJ0VERbm-HAHaE8",
          "media_fullsize":"\/\/s2.qwant.com\/thumbr\/0x0\/f\/5\/b1b1079c337366ff6b89233070ff127a86059d4e3d1641bd7bae4a01bda542\/guilty_cute_dog_puppy_trouble_accident.jpg?u=https%3A%2F%2Fwww.healthypawspetinsurance.com%2Fblog%2Fwp-content%2Fuploads%2Fguilty_cute_dog_puppy_trouble_accident.jpg&q=0&b=1&p=0&a=1",
          "thumb_type":"jpg",
          "count":79,
          "media_preview":"\/\/s2.qwant.com\/thumbr\/0x380\/7\/3\/d35a0058d81d2c0a904b16291a22afe01927de1fdf9b96025a95b10bcc4791\/guilty_cute_dog_puppy_trouble_accident.jpg?u=https%3A%2F%2Fwww.healthypawspetinsurance.com%2Fblog%2Fwp-content%2Fuploads%2Fguilty_cute_dog_puppy_trouble_accident.jpg&q=0&b=1&p=0&a=1"
        }
      ],
      "filters":{
        "size":{
          "label":"Size",
          "name":"size",
          "type":"dropdown",
          "selected":"all",
          "values":[
            {
              "value":"all",
              "label":"All",
              "translate":true
            },
            {
              "value":"small",
              "label":"Small",
              "translate":true
            },
            {
              "value":"medium",
              "label":"Medium",
              "translate":true
            },
            {
              "value":"large",
              "label":"Large",
              "translate":true
            }
          ]
        },
        "license":{
          "label":"License",
          "name":"license",
          "type":"dropdown",
          "selected":"all",
          "values":[
            {
              "value":"all",
              "label":"All",
              "translate":true
            },
            {
              "value":"public",
              "label":"Public domain",
              "translate":true
            },
            {
              "value":"share",
              "label":"Non-commercial reproduction and sharing",
              "translate":true
            },
            {
              "value":"sharecommercially",
              "label":"Reproduction and sharing",
              "translate":true
            },
            {
              "value":"modify",
              "label":"Non-commercial reproduction, sharing and modification",
              "translate":true
            },
            {
              "value":"modifycommercially",
              "label":"Reproduction, sharing and modification",
              "translate":true
            }
          ]
        },
        "freshness":{
          "label":"Freshness",
          "name":"freshness",
          "type":"dropdown",
          "selected":"all",
          "values":[
            {
              "value":"all",
              "label":"All time",
              "translate":true
            },
            {
              "value":"day",
              "label":"Past 24 hours",
              "translate":true
            },
            {
              "value":"week",
              "label":"Past week",
              "translate":true
            },
            {
              "value":"month",
              "label":"Past month",
              "translate":true
            }
          ]
        },
        "color":{
          "label":"Color",
          "name":"color",
          "type":"dropdown",
          "selected":"all",
          "values":[
            {
              "value":"all",
              "label":"All",
              "translate":true
            },
            {
              "value":"coloronly",
              "label":"Color only",
              "translate":true
            },
            {
              "value":"monochrome",
              "label":"Monochrome",
              "translate":true
            },
            {
              "value":"black",
              "label":"grid:color:black",
              "translate":false
            },
            {
              "value":"brown",
              "label":"grid:color:brown",
              "translate":false
            },
            {
              "value":"gray",
              "label":"grid:color:gray",
              "translate":false
            },
            {
              "value":"white",
              "label":"grid:color:white",
              "translate":false
            },
            {
              "value":"yellow",
              "label":"grid:color:yellow",
              "translate":false
            },
            {
              "value":"orange",
              "label":"grid:color:orange",
              "translate":false
            },
            {
              "value":"red",
              "label":"grid:color:red",
              "translate":false
            },
            {
              "value":"pink",
              "label":"grid:color:pink",
              "translate":false
            },
            {
              "value":"purple",
              "label":"grid:color:purple",
              "translate":false
            },
            {
              "value":"blue",
              "label":"grid:color:blue",
              "translate":false
            },
            {
              "value":"teal",
              "label":"grid:color:teal",
              "translate":false
            },
            {
              "value":"green",
              "label":"grid:color:green",
              "translate":false
            }
          ]
        },
        "imagetype":{
          "label":"Type",
          "name":"imagetype",
          "type":"dropdown",
          "selected":"all",
          "values":[
            {
              "value":"all",
              "label":"All",
              "translate":true
            },
            {
              "value":"animatedgif",
              "label":"Animated Gif",
              "translate":true
            },
            {
              "value":"photo",
              "label":"Photograph",
              "translate":true
            },
            {
              "value":"transparent",
              "label":"Transparent",
              "translate":true
            }
          ]
        },
        "source":{
          "label":"Source",
          "name":"source",
          "type":"dropdown",
          "selected":"web",
          "values":[
            {
              "value":"web",
              "label":"Web",
              "translate":true
            },
            {
              "value":"flickr",
              "label":"Flickr",
              "translate":false
            },
            {
              "value":"500px",
              "label":"500px",
              "translate":false
            }
          ]
        }
      },
      "domain":"web",
      "version":"B",
      "last":true
    }
  }
}
